fullofeels/__init__.py
fullofeels/__main__.py
fullofeels/builtins.py
fullofeels/ccode.py
fullofeels/codegen.py
fullofeels/i18nstr.py
fullofeels/parameter.py
fullofeels/py27.py
fullofeels/py3x.py
fullofeels/pyclass.py
fullofeels/pymember.py
fullofeels/pymethod.py
fullofeels/setupfile.py
fullofeels/visible.py
fullofeels-1.7.0.dist-info/LICENSE
fullofeels-1.7.0.dist-info/METADATA
fullofeels-1.7.0.dist-info/WHEEL
fullofeels-1.7.0.dist-info/top_level.txt
fullofeels-1.7.0.dist-info/RECORD
