Metadata-Version: 2.1
Name: fullofeels
Version: 1.7.0
Summary: Creates C code skeleton for handcrafted Python extension modules
Home-page: https://hg.sr.ht/~hfisher/fullofeels
Author: H Fisher
Author-email: hugo.fisher@gmail.com
License: UNKNOWN
Platform: UNKNOWN
Classifier: Programming Language :: Python :: 3
Classifier: License :: OSI Approved :: MIT License
Classifier: Operating System :: OS Independent
Requires-Python: >=2.7
